convertnotes/__init__.py
convertnotes/main.py
convertnotes-0.6.dist-info/METADATA
convertnotes-0.6.dist-info/WHEEL
convertnotes-0.6.dist-info/entry_points.txt
convertnotes-0.6.dist-info/top_level.txt
convertnotes-0.6.dist-info/RECORD
