Metadata-Version: 2.1
Name: convertnotes
Version: 0.6
Summary: Converts notes from one application to another
Home-page: https://github.com/dnjp/convertnotes
Author: Daniel Posthuma
Author-email: dnjp@posteo.org
Classifier: Development Status :: 3 - Alpha
Classifier: Programming Language :: Python :: 3
Classifier: License :: Public Domain
Requires-Python: >=3.11
Requires-Dist: nanoid
